SqlLoader.py
UniversalSqlBuilder.py
universal_sql_builder-0.1.0.dist-info/LICENSE
universal_sql_builder-0.1.0.dist-info/METADATA
universal_sql_builder-0.1.0.dist-info/WHEEL
universal_sql_builder-0.1.0.dist-info/top_level.txt
universal_sql_builder-0.1.0.dist-info/RECORD
