Metadata-Version: 2.1
Name: universal-sql-builder
Version: 0.1.0
Summary: Create sql query with the help of sql builder magic function help to      make automatic sql query its help in build sql query string for Microsoft SQL, MySql, SqlLite,      PostgreSQL, ORACLE, Apache Hive, Django, FLASK, HBASE and Apache Spark etc. 
Home-page: UNKNOWN
Author: Shantanu Sharma
License: UNKNOWN
Platform: UNKNOWN
Classifier: Programming Language :: Python :: 3
Classifier: License :: OSI Approved :: MIT License
Classifier: Operating System :: OS Independent
Requires-Python: >=3.0
License-File: LICENSE
